<?xml version="1.0" encoding="UTF-8" standalone="yes"?>
<sst xmlns="http://schemas.openxmlformats.org/spreadsheetml/2006/main" count="147" uniqueCount="136"><si><t>CONFIDENTIAL</t></si><si><t>The contents of this document is top secret and have been password locked.</t></si><si><t>If you are the legitimate recipient of this document, please unlock the document to display the Secret Panel.</t></si><si><t>CONFIDENTIEL</t></si><si><t>Le contenu de ce document est top secret et a donc été verrouillé par mot de passe.</t></si><si><t xml:space="preserve">Si vous êtes le destinataire légitime de ce document, veuillez le déverrouiller pour afficher le panneau secret.	</t></si><si><t>N/A</t></si><si><t>alias</t></si><si><t>Yesing</t></si><si><t>Estand</t></si><si><t>Shopeors</t></si><si><t>Jonathan Simmons</t></si><si><t>Antony Gibson</t></si><si><t>Agaton Nyberg</t></si><si><t xml:space="preserve">Benoit Boulet </t></si><si><t>Marina Yves</t></si><si><t xml:space="preserve">Laure Aime-Ipsum </t></si><si><t xml:space="preserve">Anne Itrusque </t></si><si><t>Philippe Risoli</t></si><si><t xml:space="preserve">Maxime Le Forestier </t></si><si><t xml:space="preserve">Fabien Famal </t></si><si><t xml:space="preserve">Gaël Letorney </t></si><si><t>Damien Etpasdeux</t></si><si><t>Vincent Dolarosoleil</t></si><si><t xml:space="preserve">Moundir Kolanta </t></si><si><t>Rose Purpurine</t></si><si><t xml:space="preserve">Perséphone Hadama </t></si><si><t xml:space="preserve">Mickael Gregory </t></si><si><t xml:space="preserve">Sophie Fonfec </t></si><si><t xml:space="preserve">Kemar Natolie </t></si><si><t>Raphaël Recrasques</t></si><si><t xml:space="preserve">Felix Catwoman </t></si><si><t>Bobby Marlou</t></si><si><t xml:space="preserve">Nicolas Trouplet </t></si><si><t xml:space="preserve">Céline Wozniak </t></si><si><t>Pierre Mousse</t></si><si><t>Sébastien Etpaslemien</t></si><si><t xml:space="preserve">Alix Oneill </t></si><si><t xml:space="preserve">Thibaud Nalaro </t></si><si><t xml:space="preserve">Hoshi Matara </t></si><si><t>Armand Mazoretti</t></si><si><t xml:space="preserve">Laureline Eglefin </t></si><si><t xml:space="preserve">Mathieu Traquenou </t></si><si><t>Laëticia Ponéaqua</t></si><si><t xml:space="preserve">Maxime Pöng </t></si><si><t>Quentin Banania</t></si><si><t xml:space="preserve">Samuel Marxo </t></si><si><t>Bismut Poltergesit</t></si><si><t xml:space="preserve">Bazil Persilé </t></si><si><t>Jonathan Samson</t></si><si><t xml:space="preserve">Laura Pazolini </t></si><si><t>Emmanuel Auzterlitz</t></si><si><t>Thomas Vientrois</t></si><si><t>Victor Lepaulette</t></si><si><t>Perrine Maximus</t></si><si><t>Morgane Lymew</t></si><si><t>HACK{3xcEl_R3al_Pr0TeCT10N?}</t></si><si><t>Surser</t></si><si><t>Coultoy</t></si><si><t>Burs1966</t></si><si><t>Morris</t></si><si><t>Oligh1947</t></si><si><t>Soodia</t></si><si><t>Grat2002</t></si><si><t>Shatenifely1984</t></si><si><t>Youggs</t></si><si><t>Vionfichis</t></si><si><t>Threpar</t></si><si><t>Bartaid</t></si><si><t>Sund1943</t></si><si><t>Wimen1995</t></si><si><t>Whentry</t></si><si><t>Obbes1970</t></si><si><t>Carger</t></si><si><t>Againt</t></si><si><t>Samelas</t></si><si><t>Beeforgent</t></si><si><t>Theyettept</t></si><si><t>Himps1994</t></si><si><t>Lonedity</t></si><si><t>Nonsed</t></si><si><t>Yousband</t></si><si><t>Prinel1952</t></si><si><t>Tras1939</t></si><si><t>Prolifece</t></si><si><t>Syrument</t></si><si><t>Beesse</t></si><si><t>Kepand</t></si><si><t>Dients</t></si><si><t>Prommits00</t></si><si><t>Bobject46</t></si><si><t>Weaten</t></si><si><t>Kang1973</t></si><si><t>Facce1940</t></si><si><t>Takedent</t></si><si><t>Tileords90</t></si><si><t>Whopped</t></si><si><t>Hisel1976</t></si><si><t>Suldatime</t></si><si><t>Phone</t></si><si><t>04.47.41.73.68</t></si><si><t>01.22.60.88.77</t></si><si><t>04.80.01.49.42</t></si><si><t>05.30.77.96.44</t></si><si><t>05.07.00.42.86</t></si><si><t>04.25.88.16.49</t></si><si><t>03.41.08.37.66</t></si><si><t>02.07.25.84.06</t></si><si><t>03.90.97.09.99</t></si><si><t>04.76.33.40.35</t></si><si><t>01.76.05.29.50</t></si><si><t>01.65.57.41.60</t></si><si><t>01.36.32.62.36</t></si><si><t>01.32.14.53.79</t></si><si><t>03.55.12.17.18</t></si><si><t>05.70.55.50.18</t></si><si><t>04.19.73.97.98</t></si><si><t>04.58.94.77.30</t></si><si><t>03.13.97.30.28</t></si><si><t>05.66.56.61.42</t></si><si><t>02.52.89.04.65</t></si><si><t>05.39.40.19.28</t></si><si><t>04.21.60.46.51</t></si><si><t>04.40.26.19.86</t></si><si><t>01.01.43.97.54</t></si><si><t>01.73.53.19.77</t></si><si><t>01.09.69.29.32</t></si><si><t>04.45.54.37.33</t></si><si><t>01.67.39.68.94</t></si><si><t>02.27.68.54.41</t></si><si><t>01.64.18.84.20</t></si><si><t>04.62.04.50.84</t></si><si><t>01.67.93.57.80</t></si><si><t>Name</t></si><si><t>Flag Crypto :</t></si><si><t>HACK{ImplementationErrorBreaksCiphers}</t></si></sst>